pytest_exit_code/__init__.py
pytest_exit_code/plugin.py
pytest_exit_code-0.2.0.dist-info/LICENSE
pytest_exit_code-0.2.0.dist-info/METADATA
pytest_exit_code-0.2.0.dist-info/WHEEL
pytest_exit_code-0.2.0.dist-info/entry_points.txt
pytest_exit_code-0.2.0.dist-info/top_level.txt
pytest_exit_code-0.2.0.dist-info/RECORD
