Metadata-Version: 2.1
Name: pytest-exit-code
Version: 0.2.0
Summary: A pytest plugin that overrides the built-in exit codes to retain more information about the test results.
Author-email: Sander Ploegsma <sanderploegsma@gmail.com>
Maintainer-email: Sander Ploegsma <sanderploegsma@gmail.com>
License: 
Project-URL: Repository, https://github.com/sanderploegsma/pytest-exit-code
Classifier: Framework :: Pytest
Classifier: Development Status :: 4 - Beta
Classifier: Intended Audience :: Developers
Classifier: Topic :: Software Development :: Testing
Classifier: Operating System :: OS Independent
Classifier: Programming Language :: Python
Classifier: Programming Language :: Python :: 3.8
Classifier: Programming Language :: Python :: 3.9
Classifier: Programming Language :: Python :: 3.10
Classifier: Programming Language :: Python :: 3.11
Classifier: Programming Language :: Python :: 3.12
Classifier: Programming Language :: Python :: 3 :: Only
Classifier: Programming Language :: Python :: Implementation :: CPython
Classifier: Programming Language :: Python :: Implementation :: PyPy
Classifier: License :: OSI Approved :: Apache Software License
Requires-Python: >=3.8
License-File: LICENSE
Requires-Dist: pytest >=6.2.0
